{
  "data_asset_type": null,
  "expectation_suite_name": "loan_expectations_raw",
  "expectations": [
    {
      "expectation_type": "expect_column_values_to_be_of_type",
      "kwargs": {
        "column": "customer_new_id",
        "type_": "int64"
      },
      "meta": {}
    },
    {
      "expectation_type": "expect_column_values_to_be_of_type",
      "kwargs": {
        "column": "contract_id",
        "type_": "int64"
      },
      "meta": {}
    },
    {
      "expectation_type": "expect_column_values_to_be_of_type",
      "kwargs": {
        "column": "has_default",
        "type_": "int64"
      },
      "meta": {}
    },
    {
      "expectation_type": "expect_column_values_to_be_of_type",
      "kwargs": {
        "column": "credit_amount",
        "type_": "float64"
      },
      "meta": {}
    },
    {
      "expectation_type": "expect_column_values_to_be_of_type",
      "kwargs": {
        "column": "outstanding",
        "type_": "float64"
      },
      "meta": {}
    },
    {
      "expectation_type": "expect_column_values_to_be_of_type",
      "kwargs": {
        "column": "number_of_installments_to_pay",
        "type_": "float64"
      },
      "meta": {}
    },
    {
      "expectation_type": "expect_column_values_to_be_of_type",
      "kwargs": {
        "column": "arreas",
        "type_": "float64"
      },
      "meta": {}
    },
    {
      "expectation_type": "expect_column_values_to_be_of_type",
      "kwargs": {
        "column": "date",
        "type_": "object"
      },
      "meta": {}
    },
    {
      "expectation_type": "expect_column_values_to_be_of_type",
      "kwargs": {
        "column": "segment_desc",
        "type_": "object"
      },
      "meta": {}
    },
    {
      "expectation_type": "expect_column_values_to_be_of_type",
      "kwargs": {
        "column": "credit_type",
        "type_": "object"
      },
      "meta": {}
    },
    {
      "expectation_type": "expect_column_values_to_be_of_type",
      "kwargs": {
        "column": "credit_e_o_m_start_date",
        "type_": "object"
      },
      "meta": {}
    },
    {
      "expectation_type": "expect_column_values_to_be_of_type",
      "kwargs": {
        "column": "credit_e_o_m_end_date",
        "type_": "object"
      },
      "meta": {}
    },
    {
      "expectation_type": "expect_column_values_to_be_of_type",
      "kwargs": {
        "column": "payment_frequency",
        "type_": "object"
      },
      "meta": {}
    }
  ],
  "ge_cloud_id": null,
  "meta": {
    "great_expectations_version": "0.18.12"
  }
}